django_poeditor_com_field-0.2.0.dist-info/DESCRIPTION.rst
django_poeditor_com_field-0.2.0.dist-info/METADATA
django_poeditor_com_field-0.2.0.dist-info/RECORD
django_poeditor_com_field-0.2.0.dist-info/WHEEL
django_poeditor_com_field-0.2.0.dist-info/metadata.json
django_poeditor_com_field-0.2.0.dist-info/top_level.txt
poeditor_com_field/__init__.py
poeditor_com_field/apps.py
poeditor_com_field/core.py
poeditor_com_field/fields.py
poeditor_com_field/models.py
poeditor_com_field/urls.py
poeditor_com_field/views.py
poeditor_com_field/management/__init__.py
poeditor_com_field/management/commands/__init__.py
poeditor_com_field/management/commands/sync_existing_models.py
poeditor_com_field/static/css/poeditor_com_field.css
poeditor_com_field/static/js/poeditor_com_field.js
poeditor_com_field/templates/poeditor_com_field/base.html
