Metadata-Version: 2.0
Name: django-poeditor-com-field
Version: 0.2.0
Summary: Translate your model data with poeditor.com.
Home-page: https://github.com/runekaagaard/django-poeditor-com-field
Author: Rune Kaagaard
Author-email: rumi.kg@gmail.com
License: MIT
Keywords: django-poeditor-com-field
Platform: UNKNOWN
Classifier: Development Status :: 3 - Alpha
Classifier: Framework :: Django
Classifier: Framework :: Django :: 1.8
Classifier: Framework :: Django :: 1.9
Classifier: Framework :: Django :: 1.10
Classifier: Intended Audience :: Developers
Classifier: License :: OSI Approved :: BSD License
Classifier: Natural Language :: English
Classifier: Programming Language :: Python :: 2
Classifier: Programming Language :: Python :: 2.7
Classifier: Programming Language :: Python :: 3
Classifier: Programming Language :: Python :: 3.3
Classifier: Programming Language :: Python :: 3.4
Classifier: Programming Language :: Python :: 3.5
Requires-Dist: django-model-utils (>=2.0)
